README.md
setup.cfg
setup.py
yasha/__init__.py
yasha/classes.py
yasha/cli.py
yasha/cmsis.py
yasha/filters.py
yasha/parsers.py
yasha/scons.py
yasha/tests.py
yasha/yasha.py
yasha.egg-info/PKG-INFO
yasha.egg-info/SOURCES.txt
yasha.egg-info/dependency_links.txt
yasha.egg-info/entry_points.txt
yasha.egg-info/requires.txt
yasha.egg-info/top_level.txt