Metadata-Version: 2.1
Name: yasha
Version: 5.0
Summary: A command-line tool to render Jinja templates
Home-page: https://github.com/kblomqvist/yasha
Author: Kim Blomqvist
Author-email: kblomqvist@iki.fi
License: MIT
Download-URL: https://github.com/kblomqvist/yasha/tarball/5.0
Keywords: jinja,code generator
Platform: UNKNOWN
Classifier: Topic :: Software Development :: Code Generators
Classifier: Development Status :: 5 - Production/Stable
Classifier: License :: OSI Approved :: MIT License
Classifier: Programming Language :: Python
Classifier: Programming Language :: Python :: 3
Classifier: Programming Language :: Python :: 3 :: Only
Classifier: Programming Language :: Python :: 3.6
Classifier: Programming Language :: Python :: 3.7
Classifier: Programming Language :: Python :: 3.8
Classifier: Programming Language :: Python :: 3.9
Requires-Python: >=3.6
